todoster/__init__.py
todoster/__main__.py
todoster/date_handler.py
todoster/file_operations.py
todoster/global_variables.py
todoster/list_projects.py
todoster/output_formatter.py
todoster/parser.py
todoster/project.py
todoster/show.py
todoster/task.py
todoster-1.0.0.dist-info/METADATA
todoster-1.0.0.dist-info/RECORD
todoster-1.0.0.dist-info/WHEEL
todoster-1.0.0.dist-info/entry_points.txt
todoster-1.0.0.dist-info/top_level.txt
