Metadata-Version: 2.1
Name: todoster
Version: 1.0.0
Summary: A simple command line todo list.
Home-page: https://github.com/sophieau/todoster
Author: Sophie Au
Author-email: some.person@web.de
License: MIT
Keywords: command-line-tool,productivity,todo,task-manager
Platform: UNKNOWN
Requires-Python: >=3.6
Requires-Dist: isoweek (>=1.3.3)
